<?xml version="1.0" encoding="UTF-8"?>
<rates ts="2024-02-11 14:24:40" base="GBP">
    <Currency rate="2.2919125954" live="0">
        <code>ADA</code>
        <curr>Cardano</curr>
        <loc/>
    </Currency>
    <Currency rate="4.6377910509" live="0">
        <code>AED</code>
        <curr>United Arab Emirates Dirham</curr>
        <loc>AE</loc>
    </Currency>
    <Currency rate="93.1322878987" live="0">
        <code>AFN</code>
        <curr>Afghan Afghani</curr>
        <loc>AF</loc>
    </Currency>
    <Currency rate="121.7552454244" live="0">
        <code>ALL</code>
        <curr>Albanian Lek</curr>
        <loc>AL</loc>
    </Currency>
    <Currency rate="509.5260111361" live="0">
        <code>AMD</code>
        <curr>Armenian Dram</curr>
        <loc>AM</loc>
    </Currency>
    <Currency rate="2.2565463225" live="0">
        <code>ANG</code>
        <curr>NL Antillean Guilder</curr>
        <loc>CW, SX</loc>
    </Currency>
    <Currency rate="1045.4621386968" live="0">
        <code>AOA</code>
        <curr>Angolan Kwanza</curr>
        <loc>AO</loc>
    </Currency>
    <Currency rate="0.6438594049" live="0">
        <code>ARB</code>
        <curr>Arbitrum</curr>
        <loc/>
    </Currency>
    <Currency rate="1049.8421412176" live="0">
        <code>ARS</code>
        <curr>Argentine Peso</curr>
        <loc>AR</loc>
    </Currency>
    <Currency rate="1.9359202294" live="0">
        <code>AUD</code>
        <curr>Australian Dollar</curr>
        <loc>AU, CC, CX, HM, KI, NF, NR, TV</loc>
    </Currency>
    <Currency rate="0.0313969824" live="0">
        <code>AVAX</code>
        <curr>Avalanche</curr>
        <loc/>
    </Currency>
    <Currency rate="2.2610427287" live="0">
        <code>AWG</code>
        <curr>Aruban Florin</curr>
        <loc>AW</loc>
    </Currency>
    <Currency rate="2.1473590161" live="0">
        <code>AZN</code>
        <curr>Azerbaijani Manat</curr>
        <loc>AZ</loc>
    </Currency>
    <Currency rate="2.2942388218" live="0">
        <code>BAM</code>
        <curr>Bosnia-Herzegovina Convertible Mark</curr>
        <loc>BA</loc>
    </Currency>
    <Currency rate="2.5263047248" live="0">
        <code>BBD</code>
        <curr>Barbadian Dollar</curr>
        <loc>BB</loc>
    </Currency>
    <Currency rate="138.4042765425" live="0">
        <code>BDT</code>
        <curr>Bangladeshi Taka</curr>
        <loc>BD</loc>
    </Currency>
    <Currency rate="2.288984112" live="0">
        <code>BGN</code>
        <curr>Bulgarian Lev</curr>
        <loc>BG</loc>
    </Currency>
    <Currency rate="0.4749452883" live="0">
        <code>BHD</code>
        <curr>Bahraini Dinar</curr>
        <loc>BH</loc>
    </Currency>
    <Currency rate="3604.9574612109" live="0">
        <code>BIF</code>
        <curr>Burundian Franc</curr>
        <loc>BI</loc>
    </Currency>
    <Currency rate="1.2631523624" live="0">
        <code>BMD</code>
        <curr>Bermudan Dollar</curr>
        <loc>BM</loc>
    </Currency>
    <Currency rate="0.0039111975" live="0">
        <code>BNB</code>
        <curr>Binance</curr>
        <loc/>
    </Currency>
    <Currency rate="1.6989022644" live="0">
        <code>BND</code>
        <curr>Brunei Dollar</curr>
        <loc>BN</loc>
    </Currency>
    <Currency rate="8.7263755177" live="0">
        <code>BOB</code>
        <curr>Bolivian Boliviano</curr>
        <loc>BO</loc>
    </Currency>
    <Currency rate="6.2555232177" live="0">
        <code>BRL</code>
        <curr>Brazilian Real</curr>
        <loc>BR</loc>
    </Currency>
    <Currency rate="1.2631523624" live="0">
        <code>BSD</code>
        <curr>Bahamian Dollar</curr>
        <loc>BS</loc>
    </Currency>
    <Currency rate="2.64272E-5" live="0">
        <code>BTC</code>
        <curr>Bitcoin</curr>
        <loc/>
    </Currency>
    <Currency rate="104.8772112378" live="0">
        <code>BTN</code>
        <curr>Bhutanese Ngultrum</curr>
        <loc>BT</loc>
    </Currency>
    <Currency rate="17.2711356013" live="0">
        <code>BWP</code>
        <curr>Botswanan Pula</curr>
        <loc>BW, ZW</loc>
    </Currency>
    <Currency rate="4.1356710262" live="0">
        <code>BYN</code>
        <curr>Belarusian ruble</curr>
        <loc/>
    </Currency>
    <Currency rate="41356.704107033" live="0">
        <code>BYR</code>
        <curr>Belarusian Ruble</curr>
        <loc>BY</loc>
    </Currency>
    <Currency rate="2.5263047248" live="0">
        <code>BZD</code>
        <curr>Belize Dollar</curr>
        <loc>BZ</loc>
    </Currency>
    <Currency rate="1.699887547" live="0">
        <code>CAD</code>
        <curr>Canadian Dollar</curr>
        <loc>CA</loc>
    </Currency>
    <Currency rate="3360.4667645699" live="0">
        <code>CDF</code>
        <curr>Congolese Franc</curr>
        <loc>CD</loc>
    </Currency>
    <Currency rate="1.1043995627" live="0">
        <code>CHF</code>
        <curr>Swiss Franc</curr>
        <loc>CH, LI</loc>
    </Currency>
    <Currency rate="0.0329177569" live="0">
        <code>CLF</code>
        <curr>Unidad de Fomento</curr>
        <loc>CL</loc>
    </Currency>
    <Currency rate="1225.872426817" live="0">
        <code>CLP</code>
        <curr>Chilean Peso</curr>
        <loc>CL</loc>
    </Currency>
    <Currency rate="9.0840625538" live="0">
        <code>CNY</code>
        <curr>Chinese Yuan</curr>
        <loc>CN</loc>
    </Currency>
    <Currency rate="4941.7099172287" live="0">
        <code>COP</code>
        <curr>Coombian Peso</curr>
        <loc>CO</loc>
    </Currency>
    <Currency rate="655.7423922905" live="0">
        <code>CRC</code>
        <curr>Costa Rican Colón</curr>
        <loc>CR</loc>
    </Currency>
    <Currency rate="1.2631523624" live="0">
        <code>CUC</code>
        <curr>Cuban Convertible Peso</curr>
        <loc>CU</loc>
    </Currency>
    <Currency rate="30.3156566975" live="0">
        <code>CUP</code>
        <curr>Cuban Peso</curr>
        <loc>CU</loc>
    </Currency>
    <Currency rate="129.130267974" live="0">
        <code>CVE</code>
        <curr>Cape Verdean Escudo</curr>
        <loc>CV</loc>
    </Currency>
    <Currency rate="29.5103626534" live="0">
        <code>CZK</code>
        <curr>Czech Republic Koruna</curr>
        <loc>CZ</loc>
    </Currency>
    <Currency rate="1.2634157916" live="0">
        <code>DAI</code>
        <curr>Dai</curr>
        <loc/>
    </Currency>
    <Currency rate="224.4887009973" live="0">
        <code>DJF</code>
        <curr>Djiboutian Franc</curr>
        <loc>DJ</loc>
    </Currency>
    <Currency rate="8.7300258457" live="0">
        <code>DKK</code>
        <curr>Danish Krone</curr>
        <loc>DK, FO, GL</loc>
    </Currency>
    <Currency rate="74.001652983" live="0">
        <code>DOP</code>
        <curr>Dominican Peso</curr>
        <loc>DO</loc>
    </Currency>
    <Currency rate="0.1756793029" live="0">
        <code>DOT</code>
        <curr>Polkadot</curr>
        <loc/>
    </Currency>
    <Currency rate="170.4443538652" live="0">
        <code>DZD</code>
        <curr>Algerian Dinar</curr>
        <loc>DZ</loc>
    </Currency>
    <Currency rate="39.0279781056" live="0">
        <code>EGP</code>
        <curr>Egyptian Pound</curr>
        <loc>EG, PS</loc>
    </Currency>
    <Currency rate="18.9472854359" live="0">
        <code>ERN</code>
        <curr>Eritrean Nakfa</curr>
        <loc>ER</loc>
    </Currency>
    <Currency rate="71.4163432579" live="0">
        <code>ETB</code>
        <curr>Ethiopian Birr</curr>
        <loc>ET</loc>
    </Currency>
    <Currency rate="0.0005037628" live="0">
        <code>ETH</code>
        <curr>Ethereum</curr>
        <loc/>
    </Currency>
    <Currency rate="1.1710181964" live="0">
        <code>EUR</code>
        <curr>Euro</curr>
        <loc>AD, AT, AX, BE, BL, CP, CY, DE, EA, EE, ES, EU, FI, FR, FX, GF, GP, GR, IC, IE, IT, LT,
            LU, LV, MC, ME, MF, MQ, MT, NL, PM, PT, RE, SI, SK, SM, TF, VA, XK, YT, ZW</loc>
    </Currency>
    <Currency rate="2.8325942081" live="0">
        <code>FJD</code>
        <curr>Fijian Dollar</curr>
        <loc>FJ</loc>
    </Currency>
    <Currency rate="1.0004425653" live="0">
        <code>FKP</code>
        <curr>Falkland Islands Pound</curr>
        <loc>FK</loc>
    </Currency>
    <Currency rate="1" live="0">
        <code>GBP</code>
        <curr>British Pound Sterling</curr>
        <loc>GB, GG, GS, IM, JE, TA, UK, ZW</loc>
    </Currency>
    <Currency rate="3.351042572" live="0">
        <code>GEL</code>
        <curr>Georgian Lari</curr>
        <loc>GE</loc>
    </Currency>
    <Currency rate="1.0004423805" live="0">
        <code>GGP</code>
        <curr>Guernsey pound</curr>
        <loc/>
    </Currency>
    <Currency rate="15.5382291705" live="0">
        <code>GHS</code>
        <curr>Ghanaian Cedi</curr>
        <loc>GH</loc>
    </Currency>
    <Currency rate="1.000442591" live="0">
        <code>GIP</code>
        <curr>Gibraltar Pound</curr>
        <loc>GI</loc>
    </Currency>
    <Currency rate="74.074250149" live="0">
        <code>GMD</code>
        <curr>Gambian Dalasi</curr>
        <loc>GM</loc>
    </Currency>
    <Currency rate="10813.321810266" live="0">
        <code>GNF</code>
        <curr>Guinean Franc</curr>
        <loc>GN</loc>
    </Currency>
    <Currency rate="9.8522239596" live="0">
        <code>GTQ</code>
        <curr>Guatemalan Quetzal</curr>
        <loc>GT</loc>
    </Currency>
    <Currency rate="263.8335428905" live="0">
        <code>GYD</code>
        <curr>Guyanaese Dollar</curr>
        <loc>GY</loc>
    </Currency>
    <Currency rate="9.8738235793" live="0">
        <code>HKD</code>
        <curr>Hong Kong Dollar</curr>
        <loc>HK</loc>
    </Currency>
    <Currency rate="31.1536616674" live="0">
        <code>HNL</code>
        <curr>Honduran Lempira</curr>
        <loc>HN</loc>
    </Currency>
    <Currency rate="8.8659164621" live="0">
        <code>HRK</code>
        <curr>Croatian Kuna</curr>
        <loc>HR</loc>
    </Currency>
    <Currency rate="168.7583431585" live="0">
        <code>HTG</code>
        <curr>Haitian Gourde</curr>
        <loc>HT</loc>
    </Currency>
    <Currency rate="452.4509302012" live="0">
        <code>HUF</code>
        <curr>Hungarian Forint</curr>
        <loc>HU</loc>
    </Currency>
    <Currency rate="19719.439631612" live="0">
        <code>IDR</code>
        <curr>Indonesian Rupiah</curr>
        <loc>ID</loc>
    </Currency>
    <Currency rate="4.6507633076" live="0">
        <code>ILS</code>
        <curr>Israeli New Sheqel</curr>
        <loc>IL, PS</loc>
    </Currency>
    <Currency rate="1.0004430499" live="0">
        <code>IMP</code>
        <curr>Manx pound</curr>
        <loc/>
    </Currency>
    <Currency rate="104.7982085986" live="0">
        <code>INR</code>
        <curr>Indian Rupee</curr>
        <loc>BT, IN</loc>
    </Currency>
    <Currency rate="1652.2134084022" live="0">
        <code>IQD</code>
        <curr>Iraqi Dinar</curr>
        <loc>IQ</loc>
    </Currency>
    <Currency rate="53046.10886321" live="0">
        <code>IRR</code>
        <curr>Iranian Rial</curr>
        <loc>IR</loc>
    </Currency>
    <Currency rate="173.7193455931" live="0">
        <code>ISK</code>
        <curr>Icelandic Króna</curr>
        <loc>IS</loc>
    </Currency>
    <Currency rate="1.0004421756" live="0">
        <code>JEP</code>
        <curr>Jersey pound</curr>
        <loc/>
    </Currency>
    <Currency rate="196.8534020024" live="0">
        <code>JMD</code>
        <curr>Jamaican Dollar</curr>
        <loc>JM</loc>
    </Currency>
    <Currency rate="0.8968381773" live="0">
        <code>JOD</code>
        <curr>Jordanian Dinar</curr>
        <loc>JO, PS</loc>
    </Currency>
    <Currency rate="188.5203813552" live="0">
        <code>JPY</code>
        <curr>Japanese Yen</curr>
        <loc>JP</loc>
    </Currency>
    <Currency rate="200.9965043016" live="0">
        <code>KES</code>
        <curr>Kenyan Shilling</curr>
        <loc>KE</loc>
    </Currency>
    <Currency rate="112.7412244263" live="0">
        <code>KGS</code>
        <curr>Kyrgystani Som</curr>
        <loc>KG</loc>
    </Currency>
    <Currency rate="5142.500504345" live="0">
        <code>KHR</code>
        <curr>Cambodian Riel</curr>
        <loc>KH</loc>
    </Currency>
    <Currency rate="576.7001542584" live="0">
        <code>KMF</code>
        <curr>Comorian Franc</curr>
        <loc>KM</loc>
    </Currency>
    <Currency rate="1136.822427944" live="0">
        <code>KPW</code>
        <curr>North Korean Won</curr>
        <loc>KP</loc>
    </Currency>
    <Currency rate="1677.9133935" live="0">
        <code>KRW</code>
        <curr>South Korean Won</curr>
        <loc>KR</loc>
    </Currency>
    <Currency rate="0.3877751919" live="0">
        <code>KWD</code>
        <curr>Kuwaiti Dinar</curr>
        <loc>KW</loc>
    </Currency>
    <Currency rate="1.0526227582" live="0">
        <code>KYD</code>
        <curr>Cayman Islands Dollar</curr>
        <loc>KY</loc>
    </Currency>
    <Currency rate="563.2101363829" live="0">
        <code>KZT</code>
        <curr>Kazakhstani Tenge</curr>
        <loc>KZ</loc>
    </Currency>
    <Currency rate="26318.652748832" live="0">
        <code>LAK</code>
        <curr>Laotian Kip</curr>
        <loc>LA</loc>
    </Currency>
    <Currency rate="18958.537425404" live="0">
        <code>LBP</code>
        <curr>Lebanese Pound</curr>
        <loc>LB</loc>
    </Currency>
    <Currency rate="393.5117937645" live="0">
        <code>LKR</code>
        <curr>Sri Lankan Rupee</curr>
        <loc>LK</loc>
    </Currency>
    <Currency rate="240.5054724543" live="0">
        <code>LRD</code>
        <curr>Liberian Dollar</curr>
        <loc>LR</loc>
    </Currency>
    <Currency rate="24.0359494188" live="0">
        <code>LSL</code>
        <curr>Lesotho Loti</curr>
        <loc>LS</loc>
    </Currency>
    <Currency rate="0.0178081201" live="0">
        <code>LTC</code>
        <curr>Litecoin</curr>
        <loc/>
    </Currency>
    <Currency rate="4.045021449" live="0">
        <code>LTL</code>
        <curr>Lithuanian Litas</curr>
        <loc/>
    </Currency>
    <Currency rate="0.8233435785" live="0">
        <code>LVL</code>
        <curr>Latvian Lats</curr>
        <loc/>
    </Currency>
    <Currency rate="6.1045889264" live="0">
        <code>LYD</code>
        <curr>Libyan Dinar</curr>
        <loc>LY</loc>
    </Currency>
    <Currency rate="12.6603251975" live="0">
        <code>MAD</code>
        <curr>Moroccan Dirham</curr>
        <loc>EH, MA</loc>
    </Currency>
    <Currency rate="1.4887852254" live="0">
        <code>MATIC</code>
        <curr>Matic Token</curr>
        <loc/>
    </Currency>
    <Currency rate="22.415639385" live="0">
        <code>MDL</code>
        <curr>Moldovan Leu</curr>
        <loc>MD</loc>
    </Currency>
    <Currency rate="5742.7814728433" live="0">
        <code>MGA</code>
        <curr>Malagasy Ariary</curr>
        <loc>MG</loc>
    </Currency>
    <Currency rate="72.1938435058" live="0">
        <code>MKD</code>
        <curr>Macedonian Denar</curr>
        <loc>MK</loc>
    </Currency>
    <Currency rate="2645.5353751596" live="0">
        <code>MMK</code>
        <curr>Myanma Kyat</curr>
        <loc>MM</loc>
    </Currency>
    <Currency rate="4292.803767686" live="0">
        <code>MNT</code>
        <curr>Mongolian Tugrik</curr>
        <loc>MN</loc>
    </Currency>
    <Currency rate="10.1515154343" live="0">
        <code>MOP</code>
        <curr>Macanese Pataca</curr>
        <loc>MO</loc>
    </Currency>
    <Currency rate="450.945176113" live="0">
        <code>MRO</code>
        <curr>Mauritanian ouguiya</curr>
        <loc>MR</loc>
    </Currency>
    <Currency rate="50.0565120316" live="0">
        <code>MRU</code>
        <curr>Mauritanian ouguiya</curr>
        <loc/>
    </Currency>
    <Currency rate="57.32201238" live="0">
        <code>MUR</code>
        <curr>Mauritian Rupee</curr>
        <loc>MU</loc>
    </Currency>
    <Currency rate="19.5146322908" live="0">
        <code>MVR</code>
        <curr>Maldivian Rufiyaa</curr>
        <loc>MV</loc>
    </Currency>
    <Currency rate="2125.9443173577" live="0">
        <code>MWK</code>
        <curr>Malawian Kwacha</curr>
        <loc>MW</loc>
    </Currency>
    <Currency rate="21.567244267" live="0">
        <code>MXN</code>
        <curr>Mexican Peso</curr>
        <loc>MX</loc>
    </Currency>
    <Currency rate="6.0125179047" live="0">
        <code>MYR</code>
        <curr>Malaysian Ringgit</curr>
        <loc>MY</loc>
    </Currency>
    <Currency rate="80.4533558298" live="0">
        <code>MZN</code>
        <curr>Mozambican Metical</curr>
        <loc>MZ</loc>
    </Currency>
    <Currency rate="23.9746485472" live="0">
        <code>NAD</code>
        <curr>Namibian Dollar</curr>
        <loc>NA</loc>
    </Currency>
    <Currency rate="1861.4537896529" live="0">
        <code>NGN</code>
        <curr>Nigerian Naira</curr>
        <loc>NG</loc>
    </Currency>
    <Currency rate="46.2616219542" live="0">
        <code>NIO</code>
        <curr>Nicaraguan Córdoba</curr>
        <loc>NI</loc>
    </Currency>
    <Currency rate="13.3120230634" live="0">
        <code>NOK</code>
        <curr>Norwegian Krone</curr>
        <loc>BV, NO, SJ</loc>
    </Currency>
    <Currency rate="167.3173364964" live="0">
        <code>NPR</code>
        <curr>Nepalese Rupee</curr>
        <loc>NP</loc>
    </Currency>
    <Currency rate="2.0526102705" live="0">
        <code>NZD</code>
        <curr>New Zealand Dollar</curr>
        <loc>CK, NU, NZ, PN, TK</loc>
    </Currency>
    <Currency rate="0.4850379474" live="0">
        <code>OMR</code>
        <curr>Omani Rial</curr>
        <loc>OM</loc>
    </Currency>
    <Currency rate="0.3756681745" live="0">
        <code>OP</code>
        <curr>Optimism</curr>
        <loc/>
    </Currency>
    <Currency rate="1.261611519" live="0">
        <code>PAB</code>
        <curr>Panamanian Balboa</curr>
        <loc>PA</loc>
    </Currency>
    <Currency rate="4.8887542232" live="0">
        <code>PEN</code>
        <curr>Peruvian Nuevo Sol</curr>
        <loc>PE</loc>
    </Currency>
    <Currency rate="4.7427843841" live="0">
        <code>PGK</code>
        <curr>Papua New Guinean Kina</curr>
        <loc>PG</loc>
    </Currency>
    <Currency rate="70.5856491863" live="0">
        <code>PHP</code>
        <curr>Philippine Peso</curr>
        <loc>PH</loc>
    </Currency>
    <Currency rate="352.7597222543" live="0">
        <code>PKR</code>
        <curr>Pakistani Rupee</curr>
        <loc>PK</loc>
    </Currency>
    <Currency rate="5.0629935217" live="0">
        <code>PLN</code>
        <curr>Polish Zloty</curr>
        <loc>PL</loc>
    </Currency>
    <Currency rate="9225.0987516865" live="0">
        <code>PYG</code>
        <curr>Paraguayan Guarani</curr>
        <loc>PY</loc>
    </Currency>
    <Currency rate="4.5967636362" live="0">
        <code>QAR</code>
        <curr>Qatari Rial</curr>
        <loc>QA</loc>
    </Currency>
    <Currency rate="5.8271627921" live="0">
        <code>RON</code>
        <curr>Romanian Leu</curr>
        <loc>RO</loc>
    </Currency>
    <Currency rate="136.7132692087" live="0">
        <code>RSD</code>
        <curr>Serbian Dinar</curr>
        <loc>RS</loc>
    </Currency>
    <Currency rate="115.3792315724" live="0">
        <code>RUB</code>
        <curr>Russian Ruble</curr>
        <loc>RU, SU</loc>
    </Currency>
    <Currency rate="1606.2532435305" live="0">
        <code>RWF</code>
        <curr>Rwandan Franc</curr>
        <loc>RW</loc>
    </Currency>
    <Currency rate="4.7298492565" live="0">
        <code>SAR</code>
        <curr>Saudi Riyal</curr>
        <loc>SA</loc>
    </Currency>
    <Currency rate="10.6775627778" live="0">
        <code>SBD</code>
        <curr>Solomon Islands Dollar</curr>
        <loc>SB</loc>
    </Currency>
    <Currency rate="18.1433425066" live="0">
        <code>SCR</code>
        <curr>Seychellois Rupee</curr>
        <loc>SC</loc>
    </Currency>
    <Currency rate="759.7861459808" live="0">
        <code>SDG</code>
        <curr>Sudanese Pound</curr>
        <loc>SD</loc>
    </Currency>
    <Currency rate="13.1986298684" live="0">
        <code>SEK</code>
        <curr>Swedish Krona</curr>
        <loc>SE</loc>
    </Currency>
    <Currency rate="1.6987760097" live="0">
        <code>SGD</code>
        <curr>Singapore Dollar</curr>
        <loc>SG</loc>
    </Currency>
    <Currency rate="0.9999999351" live="0">
        <code>SHP</code>
        <curr>Saint Helena Pound</curr>
        <loc>SH</loc>
    </Currency>
    <Currency rate="28712.859186826" live="0">
        <code>SLL</code>
        <curr>Sierra Leonean Leone</curr>
        <loc>SL</loc>
    </Currency>
    <Currency rate="0.011587783" live="0">
        <code>SOL</code>
        <curr>Solana</curr>
        <loc/>
    </Currency>
    <Currency rate="721.7774612852" live="0">
        <code>SOS</code>
        <curr>Somali Shilling</curr>
        <loc>SO</loc>
    </Currency>
    <Currency rate="45.8394915389" live="0">
        <code>SRD</code>
        <curr>Surinamese Dollar</curr>
        <loc>SR</loc>
    </Currency>
    <Currency rate="28735.933333706" live="0">
        <code>STD</code>
        <curr>São Tomé and Príncipe dobra</curr>
        <loc>ST</loc>
    </Currency>
    <Currency rate="28.7359392386" live="0">
        <code>STN</code>
        <curr>São Tomé and Príncipe dobra</curr>
        <loc/>
    </Currency>
    <Currency rate="11.052583171" live="0">
        <code>SVC</code>
        <curr>Salvadoran Colón</curr>
        <loc/>
    </Currency>
    <Currency rate="16422.770448985" live="0">
        <code>SYP</code>
        <curr>Syrian Pound</curr>
        <loc>SY</loc>
    </Currency>
    <Currency rate="24.0306432068" live="0">
        <code>SZL</code>
        <curr>Swazi Lilangeni</curr>
        <loc>SZ</loc>
    </Currency>
    <Currency rate="45.3387909047" live="0">
        <code>THB</code>
        <curr>Thai Baht</curr>
        <loc>TH</loc>
    </Currency>
    <Currency rate="13.8273264673" live="0">
        <code>TJS</code>
        <curr>Tajikistani Somoni</curr>
        <loc>TJ</loc>
    </Currency>
    <Currency rate="4.4210332684" live="0">
        <code>TMT</code>
        <curr>Turkmenistani Manat</curr>
        <loc>TM</loc>
    </Currency>
    <Currency rate="3.952530759" live="0">
        <code>TND</code>
        <curr>Tunisian Dinar</curr>
        <loc>TN</loc>
    </Currency>
    <Currency rate="2.9334949136" live="0">
        <code>TOP</code>
        <curr>Tongan Paʻanga</curr>
        <loc>TO</loc>
    </Currency>
    <Currency rate="38.7588777079" live="0">
        <code>TRY</code>
        <curr>Turkish Lira</curr>
        <loc>TR</loc>
    </Currency>
    <Currency rate="8.5727514628" live="0">
        <code>TTD</code>
        <curr>Trinidad and Tobago Dollar</curr>
        <loc>TT</loc>
    </Currency>
    <Currency rate="39.6604776436" live="0">
        <code>TWD</code>
        <curr>New Taiwan Dollar</curr>
        <loc>TW</loc>
    </Currency>
    <Currency rate="3185.3365823054" live="0">
        <code>TZS</code>
        <curr>Tanzanian Shilling</curr>
        <loc>TZ</loc>
    </Currency>
    <Currency rate="47.6069925851" live="0">
        <code>UAH</code>
        <curr>Ukrainian Hryvnia</curr>
        <loc>UA</loc>
    </Currency>
    <Currency rate="4811.4897774965" live="0">
        <code>UGX</code>
        <curr>Ugandan Shilling</curr>
        <loc>UG</loc>
    </Currency>
    <Currency rate="1.2631523624" live="1">
        <code>USD</code>
        <curr>US Dollar</curr>
        <loc>AC, AS, BQ, DG, EC, FM, GU, HT, IO, MH, MP, PA, PR, PW, SV, TC, TL, UM, US, VG, VI, ZW</loc>
    </Currency>
    <Currency rate="1.2667678312" live="0">
        <code>USDC</code>
        <curr>USD Coin</curr>
        <loc/>
    </Currency>
    <Currency rate="1.2638059841" live="0">
        <code>USDT</code>
        <curr>Tether</curr>
        <loc/>
    </Currency>
    <Currency rate="49.5826041732" live="0">
        <code>UYU</code>
        <curr>Uruguayan Peso</curr>
        <loc>UY</loc>
    </Currency>
    <Currency rate="15755.431145331" live="0">
        <code>UZS</code>
        <curr>Uzbekistan Som</curr>
        <loc>UZ</loc>
    </Currency>
    <Currency rate="4566577.8373561" live="0">
        <code>VEF</code>
        <curr>Venezuelan Bolívar</curr>
        <loc>VE</loc>
    </Currency>
    <Currency rate="45.6657891787" live="0">
        <code>VES</code>
        <curr>Venezuelan Bolívar</curr>
        <loc/>
    </Currency>
    <Currency rate="30804.961195654" live="0">
        <code>VND</code>
        <curr>Vietnamese Dong</curr>
        <loc>VN</loc>
    </Currency>
    <Currency rate="151.5072058244" live="0">
        <code>VUV</code>
        <curr>Vanuatu Vatu</curr>
        <loc>VU</loc>
    </Currency>
    <Currency rate="3.4720246655" live="0">
        <code>WST</code>
        <curr>Samoan Tala</curr>
        <loc>WS</loc>
    </Currency>
    <Currency rate="768.1335158351" live="0">
        <code>XAF</code>
        <curr>CFA Franc BEAC</curr>
        <loc>CF, CG, CM, GA, GQ, TD</loc>
    </Currency>
    <Currency rate="0.0558656237" live="0">
        <code>XAG</code>
        <curr>Silver Ounce</curr>
        <loc/>
    </Currency>
    <Currency rate="0.0006239384" live="0">
        <code>XAU</code>
        <curr>Gold Ounce</curr>
        <loc/>
    </Currency>
    <Currency rate="3.4105113785" live="0">
        <code>XCD</code>
        <curr>East Caribbean Dollar</curr>
        <loc>AG, AI, DM, GD, KN, LC, MS, VC</loc>
    </Currency>
    <Currency rate="0.9513433058" live="0">
        <code>XDR</code>
        <curr>Special drawing rights</curr>
        <loc/>
    </Currency>
    <Currency rate="768.1335613172" live="0">
        <code>XOF</code>
        <curr>CFA Franc BCEAO</curr>
        <loc>BF, BJ, CI, GW, ML, NE, SN, TG</loc>
    </Currency>
    <Currency rate="0.0014141894" live="0">
        <code>XPD</code>
        <curr>Palladium Ounce</curr>
        <loc/>
    </Currency>
    <Currency rate="139.6072859269" live="0">
        <code>XPF</code>
        <curr>CFP Franc</curr>
        <loc>NC, PF, WF</loc>
    </Currency>
    <Currency rate="0.0014174103" live="0">
        <code>XPT</code>
        <curr>Platinum Ounce</curr>
        <loc/>
    </Currency>
    <Currency rate="2.3897475801" live="0">
        <code>XRP</code>
        <curr>Ripple</curr>
        <loc/>
    </Currency>
    <Currency rate="315.4816227999" live="0">
        <code>YER</code>
        <curr>Yemeni Rial</curr>
        <loc>YE</loc>
    </Currency>
    <Currency rate="24.0272468019" live="0">
        <code>ZAR</code>
        <curr>South African Rand</curr>
        <loc>LS, NA, ZA, ZW</loc>
    </Currency>
    <Currency rate="11369.887044394" live="0">
        <code>ZMK</code>
        <curr>Zambian Kwacha</curr>
        <loc/>
    </Currency>
    <Currency rate="34.0930700254" live="0">
        <code>ZMW</code>
        <curr>Zambian Kwacha</curr>
        <loc>ZM</loc>
    </Currency>
    <Currency rate="457.1348399509" live="0">
        <code>ZWL</code>
        <curr>Zimbabwean dollar</curr>
        <loc/>
    </Currency>
</rates>
